{
"users":[],
"quranic_reflect":[
{
    "id": 1,
    "title": "First quranic_reflect",
    "body": "Body of the first quranic_reflect",
    "status": "published",
    "createdAt": "2023-09-13T11:01:00.120Z",
    "updatedAt": "2023-09-13T11:01:00.120Z",
    "author":{
        "id":1
    }
},
{
    "id": 2,
    "title": "Second quranic_reflect",
    "body": "Body of the second quranic_reflect",
    "status": "published",
    "createdAt": "2023-09-13T11:01:00.120Z",
    "updatedAt": "2023-09-13T11:01:00.120Z",
    "author":{
        "id":2
    }
},
{
    "id": 3,
    "authorId": 3,
    "title": "3rd quranic_reflect",
    "body": "Body of the 3rd quranic_reflect",
    "status": "published",
    "createdAt": "2023-09-13T11:01:00.120Z",
    "updatedAt": "2023-09-13T11:01:00.120Z",
    "author":{
        "id":3
    }
}

],
"comments":[]
}